vomero/__init__.py
vomero/py.typed
vomero/streams.py
vomero/types.py
vomero/worker.py
vomero-0.1.6.dist-info/LICENSE
vomero-0.1.6.dist-info/METADATA
vomero-0.1.6.dist-info/WHEEL
vomero-0.1.6.dist-info/RECORD
