Metadata-Version: 2.1
Name: vomero
Version: 0.1.6
Summary: Event processing library for Python based on Redis Streams
Home-page: https://github.com/mzsawicki/vomero
License: MIT
Author: Marcin Sawicki
Author-email: marcin.z.sawicki@protonmail.com
Requires-Python: >=3.11,<4.0
Classifier: License :: OSI Approved :: MIT License
Classifier: Programming Language :: Python :: 3
Classifier: Programming Language :: Python :: 3.11
Classifier: Programming Language :: Python :: 3.12
Requires-Dist: redis (>=5.0.3)
